glasspy/__init__.py
glasspy/chemistry/__init__.py
glasspy/chemistry/convert.py
glasspy/chemistry/data.py
glasspy/chemistry/featurizer.py
glasspy/chemistry/types.py
glasspy/chemistry/data/chemical_properties.csv
glasspy/data/__init__.py
glasspy/data/load.py
glasspy/data/translators.py
glasspy/predict/__init__.py
glasspy/predict/base.py
glasspy/predict/models.py
glasspy/viscosity/__init__.py
glasspy/viscosity/diffusion.py
glasspy/viscosity/equilibrium.py
glasspy/viscosity/equilibrium_log.py
glasspy-0.5.3.dist-info/LICENSE
glasspy-0.5.3.dist-info/METADATA
glasspy-0.5.3.dist-info/WHEEL
glasspy-0.5.3.dist-info/top_level.txt
glasspy-0.5.3.dist-info/RECORD
