Metadata-Version: 2.1
Name: glasspy
Version: 0.5.3
Summary: Python module for scientists working with glass materials
Home-page: https://github.com/drcassar/glasspy
Author: Daniel Roberto Cassar
Author-email: daniel.r.cassar@gmail.com
License: GPL
Keywords: glass,non-crystalline materials
Classifier: Programming Language :: Python :: 3.10
Classifier: Programming Language :: Python :: 3.11
Classifier: Programming Language :: Python :: 3.12
Classifier: License :: OSI Approved :: GNU General Public License v3 or later (GPLv3+)
Classifier: Operating System :: OS Independent
Classifier: Development Status :: 3 - Alpha
Classifier: Topic :: Scientific/Engineering
Classifier: Intended Audience :: Science/Research
Classifier: Environment :: Console
Requires-Python: >=3.10
License-File: LICENSE
Requires-Dist: pandas >=2.0.0
Requires-Dist: lmfit >=1.2.0
Requires-Dist: chemparse >=0.1.0
Requires-Dist: scikit-learn >=1.5.0
Requires-Dist: compress-pickle >=2.1.0
Requires-Dist: torch
Requires-Dist: lightning >=2.1.0
Requires-Dist: platformdirs
Requires-Dist: requests
